{
  "Heart Flute On A New Moon": "2025-08-10",
  "The Wicked Don't Rest": "2025-08-13",
  "A Night Awake": "2025-08-13"
  "house": "2025-08-13"
  "Lightyears": "2025-08-13"
  "Run": "2025-08-13"
  "Safeway": "2025-08-13"
  "That's Right": "2025-08-13"
  "The Dreamscape": "2025-08-13"
  "Victory is Ours": "2025-08-13"
  "1:1": "2025-08-13"
  "walking": "2025-08-13"
  "Bag O' Bones Druid": "2025-18-14"
  "Galactic Signals": "2028-08-14"
  "Protocol": "2025-08-14"
  "Smooth": "2028-08-16"
  "Summon the Shifters": "2025-08-20"
  "dripping": "2025-09-06"
  "From the Devil's Fires": 2025-09-30"
  "Live Mixes 001": "2025-10-29"
  "Call the Dead": "2025-10-29"
  "Protection Chant": "2025-10-30"
  "Samhain Soundscape '25": "2025-10-30"
  "2460966.6528": "2025-11-01"
  "On the Mount": "2025-11-2025"
  "EL3CTROSW1NG": "2025-12-02"
  "sAlt": "2025-12-10"
  "eNERGYHEX": "2025-12-02"
  "r3seT": "2025-12-02"
}
